TokenBuffer.py
__init__.py
tokenizer.py
tokenbuffer-0.1.4.dist-info/METADATA
tokenbuffer-0.1.4.dist-info/WHEEL
tokenbuffer-0.1.4.dist-info/top_level.txt
tokenbuffer-0.1.4.dist-info/RECORD
